<annotation>
	<folder>1</folder>
	<filename>video_1046.jpg</filename>
	<path>/Users/vaibhavpatel/Desktop/final_deep_learning/assignemnt3/1/video_1046.jpg</path>
	<source>
		<database>Unknown</database>
	</source>
	<size>
		<width>720</width>
		<height>1280</height>
		<depth>3</depth>
	</size>
	<segmented>0</segmented>
	<object>
		<name>road works sign board</name>
		<pose>Unspecified</pose>
		<truncated>0</truncated>
		<difficult>0</difficult>
		<bndbox>
			<xmin>18</xmin>
			<ymin>419</ymin>
			<xmax>127</xmax>
			<ymax>488</ymax>
		</bndbox>
	</object>
	<object>
		<name>road works sign board</name>
		<pose>Unspecified</pose>
		<truncated>0</truncated>
		<difficult>0</difficult>
		<bndbox>
			<xmin>137</xmin>
			<ymin>427</ymin>
			<xmax>193</xmax>
			<ymax>488</ymax>
		</bndbox>
	</object>
	<object>
		<name>road cone</name>
		<pose>Unspecified</pose>
		<truncated>0</truncated>
		<difficult>0</difficult>
		<bndbox>
			<xmin>308</xmin>
			<ymin>405</ymin>
			<xmax>327</xmax>
			<ymax>438</ymax>
		</bndbox>
	</object>
</annotation>
